curatorbin/__init__.py
curatorbin/arm/curator
curatorbin/macos/curator
curatorbin/macos-arm64/curator
curatorbin/ubuntu/curator
curatorbin/windows-64/curator.exe
curatorbin-1.2.4.dist-info/METADATA
curatorbin-1.2.4.dist-info/WHEEL
curatorbin-1.2.4.dist-info/top_level.txt
curatorbin-1.2.4.dist-info/RECORD
