Metadata-Version: 2.1
Name: curatorbin
Version: 1.2.4
Summary: install curator through pip and run it through python
Home-page: https://github.com/evergreen-ci/curatorbin
Author: Harris Hoke
Author-email: harris.hoke@mongodb.com
License: SSPLv1
Platform: UNKNOWN
Classifier: Environment :: Console
Classifier: Operating System :: MacOS :: MacOS X
Classifier: Operating System :: Microsoft :: Windows
Classifier: Operating System :: POSIX :: Linux
Classifier: Programming Language :: Python
Classifier: Programming Language :: Python :: 3.9
